{"otherData": {},"traceEvents":[{"cat":"function","dur":2,"name":"__cdecl PolyEngine::OpenGLTexture2D::~OpenGLTexture2D(void)","ph":"X","pid":0,"tid":18109276369754742965,"ts":953457079469},{"cat":"function","dur":0,"name":"__cdecl PolyEngine::OpenGLShader::~OpenGLShader(void)","ph":"X","pid":0,"tid":18109276369754742965,"ts":953457079529},{"cat":"function","dur":1,"name":"__cdecl PolyEngine::OpenGLVertexArray::~OpenGLVertexArray(void)","ph":"X","pid":0,"tid":18109276369754742965,"ts":953457079562},{"cat":"function","dur":6,"name":"__cdecl PolyEngine::OpenGLIndexBuffer::~OpenGLIndexBuffer(void)","ph":"X","pid":0,"tid":18109276369754742965,"ts":953457079592},{"cat":"function","dur":0,"name":"__cdecl PolyEngine::OpenGLVertexBuffer::~OpenGLVertexBuffer(void)","ph":"X","pid":0,"tid":18109276369754742965,"ts":953457079630},{"cat":"function","dur":198,"name":"void __cdecl PolyEngine::Renderer2D::Shutdown(void)","ph":"X","pid":0,"tid":18109276369754742965,"ts":953457079467},{"cat":"function","dur":228,"name":"__cdecl PolyEngine::Application::~Application(void)","ph":"X","pid":0,"tid":18109276369754742965,"ts":953457079466},{"cat":"function","dur":0,"name":"void __cdecl Sandbox2D::OnDetach(void)","ph":"X","pid":0,"tid":18109276369754742965,"ts":953457079722},{"cat":"function","dur":0,"name":"__cdecl PolyEngine::OpenGLTexture2D::~OpenGLTexture2D(void)","ph":"X","pid":0,"tid":18109276369754742965,"ts":953457079757},{"cat":"function","dur":0,"name":"__cdecl PolyEngine::OpenGLTexture2D::~OpenGLTexture2D(void)","ph":"X","pid":0,"tid":18109276369754742965,"ts":953457079787},{"cat":"function","dur":0,"name":"__cdecl PolyEngine::OpenGLTexture2D::~OpenGLTexture2D(void)","ph":"X","pid":0,"tid":18109276369754742965,"ts":953457079816},{"cat":"function","dur":931,"name":"void __cdecl PolyEngine::ImGuiLayer::OnDetach(void)","ph":"X","pid":0,"tid":18109276369754742965,"ts":953457079846},{"cat":"function","dur":9158,"name":"void __cdecl PolyEngine::WindowsWindow::Shutdown(void)","ph":"X","pid":0,"tid":18109276369754742965,"ts":953457080834},{"cat":"function","dur":9299,"name":"__cdecl PolyEngine::WindowsWindow::~WindowsWindow(void)","ph":"X","pid":0,"tid":18109276369754742965,"ts":953457080834}]}